automlbench/__init__.py
automlbench/data_loader.py
automlbench/evaluation.py
automlbench/hyperparameter_tuning.py
automlbench/model_train.py
automlbench/models.py
automlbench/preprocessing.py
automlbench/untitled.txt
automlbench/utils.py
automlbench/visualization.py
automlbench-0.1.5.dist-info/METADATA
automlbench-0.1.5.dist-info/WHEEL
automlbench-0.1.5.dist-info/entry_points.txt
automlbench-0.1.5.dist-info/top_level.txt
automlbench-0.1.5.dist-info/RECORD
