Metadata-Version: 2.1
Name: automlbench
Version: 0.1.5
Summary: A Python package for automated ML model benchmarking and comparison
Home-page: https://github.com/AnnNaserNabil/automlbench
Author: Ann Naser Nabil
Author-email: Ann Naser Nabil <ann.n.nabil@gmail.com>
License: MIT
Project-URL: Homepage, https://github.com/AnnNaserNabil/automlbench
Project-URL: Documentation, https://github.com/AnnNaserNabil/automlbench/wiki
Project-URL: Repository, https://github.com/AnnNaserNabil/automlbench
Project-URL: Issues, https://github.com/AnnNaserNabil/automlbench/issues
Requires-Python: >=3.7
Requires-Dist: numpy
Requires-Dist: pandas
Requires-Dist: scikit-learn
Requires-Dist: matplotlib
Requires-Dist: seaborn
Requires-Dist: xgboost
Requires-Dist: lightgbm
Requires-Dist: shap
Requires-Dist: lime
Requires-Dist: catboost
Requires-Dist: imbalanced-learn
